README.md
setup.cfg
setup.py
n_vy_distributions/Binomialdistribution.py
n_vy_distributions/Gaussiandistribution.py
n_vy_distributions/Generaldistribution.py
n_vy_distributions/__init__.py
n_vy_distributions.egg-info/PKG-INFO
n_vy_distributions.egg-info/SOURCES.txt
n_vy_distributions.egg-info/dependency_links.txt
n_vy_distributions.egg-info/not-zip-safe
n_vy_distributions.egg-info/top_level.txt